mujoco/__init__.py
mujoco/sim.cpython-36m-darwin.so
mujoco/simGlfw.cpython-36m-darwin.so
mujoco.sim-1.0.3.dist-info/DESCRIPTION.rst
mujoco.sim-1.0.3.dist-info/METADATA
mujoco.sim-1.0.3.dist-info/RECORD
mujoco.sim-1.0.3.dist-info/WHEEL
mujoco.sim-1.0.3.dist-info/metadata.json
mujoco.sim-1.0.3.dist-info/top_level.txt
